{
    "shapes": [
      { "id": 1, "type": "round" },
      { "id": 2, "type": "square" }
    ],
    "food": [
      { "id": 1, "type": "fruit" },
      { "id": 2, "type": "vegetable" }
    ],
    "speed": [
      { "id": 3, "type": "slow" },
      { "id": 1, "type": "normal" },
      { "id": 2, "type": "fast" }
    ],
    "fruit" : [
        { "id": 1, "type": "apple", "color": "red" },
        { "id": 2, "type": "cherry", "color": "dark red" },
        { "id": 3, "type": "plum", "color": "purple" },
        { "id": 4, "type": "raspberry", "color": "pink" }
    ],
    "vegetable" : [
        { "id": 1, "type": "carrot", "color": "orange" },
        { "id": 2, "type": "cabbage", "color": "dark green" },
        { "id": 3, "type": "cucumber", "color": "light green" },
        { "id": 4, "type": "eggplant", "color": "purple" }
    ]
  }